ZhiyaoHuihuxiJiunengZuomingxiang/Dockerfile
ZhiyaoHuihuxiJiunengZuomingxiang/README.md
ZhiyaoHuihuxiJiunengZuomingxiang/__init__.py
ZhiyaoHuihuxiJiunengZuomingxiang/__main__.py
ZhiyaoHuihuxiJiunengZuomingxiang/file.epub
ZhiyaoHuihuxiJiunengZuomingxiang/index.html
ZhiyaoHuihuxiJiunengZuomingxiang/css/__init__.py
ZhiyaoHuihuxiJiunengZuomingxiang/css/annotations.css
ZhiyaoHuihuxiJiunengZuomingxiang/css/main.css
ZhiyaoHuihuxiJiunengZuomingxiang/css/normalize.css
ZhiyaoHuihuxiJiunengZuomingxiang/css/popup.css
ZhiyaoHuihuxiJiunengZuomingxiang/font/__init__.py
ZhiyaoHuihuxiJiunengZuomingxiang/font/fontello.eot
ZhiyaoHuihuxiJiunengZuomingxiang/font/fontello.svg
ZhiyaoHuihuxiJiunengZuomingxiang/font/fontello.ttf
ZhiyaoHuihuxiJiunengZuomingxiang/font/fontello.woff
ZhiyaoHuihuxiJiunengZuomingxiang/img/__init__.py
ZhiyaoHuihuxiJiunengZuomingxiang/img/annotator-glyph-sprite.png
ZhiyaoHuihuxiJiunengZuomingxiang/img/annotator-icon-sprite.png
ZhiyaoHuihuxiJiunengZuomingxiang/img/apple-touch-icon.png
ZhiyaoHuihuxiJiunengZuomingxiang/img/cancelfullscreen.png
ZhiyaoHuihuxiJiunengZuomingxiang/img/close.png
ZhiyaoHuihuxiJiunengZuomingxiang/img/fullscreen.png
ZhiyaoHuihuxiJiunengZuomingxiang/img/loader.gif
ZhiyaoHuihuxiJiunengZuomingxiang/img/menu-icon.png
ZhiyaoHuihuxiJiunengZuomingxiang/img/save.png
ZhiyaoHuihuxiJiunengZuomingxiang/img/saved.png
ZhiyaoHuihuxiJiunengZuomingxiang/img/settings-s.png
ZhiyaoHuihuxiJiunengZuomingxiang/img/settings.png
ZhiyaoHuihuxiJiunengZuomingxiang/img/star.png
ZhiyaoHuihuxiJiunengZuomingxiang/js/__init__.py
ZhiyaoHuihuxiJiunengZuomingxiang/js/epub.js
ZhiyaoHuihuxiJiunengZuomingxiang/js/epub.min.js
ZhiyaoHuihuxiJiunengZuomingxiang/js/epub.min.map
ZhiyaoHuihuxiJiunengZuomingxiang/js/hooks.min.js
ZhiyaoHuihuxiJiunengZuomingxiang/js/hooks.min.map
ZhiyaoHuihuxiJiunengZuomingxiang/js/reader.js
ZhiyaoHuihuxiJiunengZuomingxiang/js/reader.js.map
ZhiyaoHuihuxiJiunengZuomingxiang/js/reader.min.js
ZhiyaoHuihuxiJiunengZuomingxiang/js/reader.min.map
zhiyao_huihuxi_jiuneng_zuomingxiang-2022.10.9.1.dist-info/METADATA
zhiyao_huihuxi_jiuneng_zuomingxiang-2022.10.9.1.dist-info/WHEEL
zhiyao_huihuxi_jiuneng_zuomingxiang-2022.10.9.1.dist-info/entry_points.txt
zhiyao_huihuxi_jiuneng_zuomingxiang-2022.10.9.1.dist-info/top_level.txt
zhiyao_huihuxi_jiuneng_zuomingxiang-2022.10.9.1.dist-info/RECORD
